arx_tools/__init__.py
arx_tools/download_ncbi_genome.py
arx_tools/folder_looper.py
arx_tools/genbank_to_fasta.py
arx_tools/import_genome.py
arx_tools/import_orthofinder.py
arx_tools/init_folder_structure.py
arx_tools/init_orthofinder.py
arx_tools/metadata_schemas.py
arx_tools/parse_busco.py
arx_tools/reindex_assembly.py
arx_tools/rename_custom_annotations.py
arx_tools/rename_eggnog.py
arx_tools/rename_fasta.py
arx_tools/rename_genbank.py
arx_tools/rename_gff.py
arx_tools/update_folder_structure.py
arx_tools/utils.py
arx_tools/data/COG_categories.json
arx_tools/data/annotations.json
arx_tools-1.0.0.dist-info/licenses/LICENCE.md
arx_tools-1.0.0.dist-info/METADATA
arx_tools-1.0.0.dist-info/WHEEL
arx_tools-1.0.0.dist-info/entry_points.txt
arx_tools-1.0.0.dist-info/top_level.txt
arx_tools-1.0.0.dist-info/RECORD
