Metadata-Version: 2.4
Name: arx-tools
Version: 1.0.0
Summary: Set of scripts to aid Arx administrators import data
Home-page: https://github.com/Abrinca/arx-tools
Author: Abrinca
Author-email: info@abrinca.com
License: MIT
Classifier: License :: OSI Approved :: MIT License
Classifier: Programming Language :: Python :: 3
Classifier: Programming Language :: Python :: 3.9
License-File: LICENCE.md
Requires-Dist: schema
Requires-Dist: biopython
Requires-Dist: termcolor
Requires-Dist: fire
Requires-Dist: pyyaml
Dynamic: author
Dynamic: author-email
Dynamic: classifier
Dynamic: description
Dynamic: description-content-type
Dynamic: home-page
Dynamic: license
Dynamic: license-file
Dynamic: requires-dist
Dynamic: summary
